.gitignore
CONTRIBUTING.md
LICENSE
MANIFEST.in
NEWS
README.md
setup.py
clant/__init__.py
clant/clant.py
clant.egg-info/PKG-INFO
clant.egg-info/SOURCES.txt
clant.egg-info/dependency_links.txt
clant.egg-info/entry_points.txt
clant.egg-info/top_level.txt