Metadata-Version: 2.1
Name: clant
Version: 2.0.0
Summary: A unified frontend for clang linting tools
Home-page: https://gitlab.com/drobilla/clant
Author: David Robillard
Author-email: d@drobilla.net
License: ISC
Classifier: Development Status :: 5 - Production/Stable
Classifier: Intended Audience :: Developers
Classifier: License :: OSI Approved :: ISC License (ISCL)
Classifier: Operating System :: POSIX
Classifier: Programming Language :: C
Classifier: Programming Language :: C++
Classifier: Programming Language :: Objective C
Classifier: Programming Language :: Python :: 3.4
Classifier: Programming Language :: Python :: 3.5
Classifier: Programming Language :: Python :: 3.6
Classifier: Programming Language :: Python :: 3.7
Classifier: Programming Language :: Python :: 3.8
License-File: LICENSE
